tests/__init__.py
tests/test_client.py
tests/test_config.py
tests/test_context.py
togglr/__init__.py
togglr/cache.py
togglr/cli.py
togglr/client.py
togglr/config.py
togglr/context.py
togglr/errors.py
togglr/track_event.py
togglr/version.py
togglr_sdk-1.1.0.dist-info/METADATA
togglr_sdk-1.1.0.dist-info/WHEEL
togglr_sdk-1.1.0.dist-info/top_level.txt
togglr_sdk-1.1.0.dist-info/RECORD
