Metadata-Version: 2.4
Name: togglr-sdk
Version: 1.1.0
Summary: SDK for Togglr feature flags management system
Home-page: https://github.com/togglr-project/togglr-sdk-python
Author: Roman Chudov
Author-email: Roman Chudov <roman.chudov@gmail.com>
Maintainer-email: Roman Chudov <roman.chudov@gmail.com>
License-Expression: MIT
Project-URL: Homepage, https://github.com/togglr-project/togglr-sdk-python
Project-URL: Documentation, https://github.com/togglr-project/togglr-sdk-python
Project-URL: Repository, https://github.com/togglr-project/togglr-sdk-python.git
Keywords: sdk,togglr,feature-flag
Classifier: Programming Language :: Python
Requires-Python: >=3.8
Requires-Dist: httpx
Requires-Dist: pydantic
Requires-Dist: typing-extensions
Requires-Dist: cachetools
Dynamic: author
Dynamic: home-page
Dynamic: requires-python
